.gitignore
LICENSE
README.md
requirements.txt
setup.py
Jupyter notebooks/contour_raster.ipynb
Jupyter notebooks/france_power_grid_rte.ipynb
Jupyter notebooks/france_power_stations_rte.ipynb
Jupyter notebooks/france_rte_power_lines.ipynb
Jupyter notebooks/fuel_consumption.ipynb
Jupyter notebooks/monthly_ghi_sum.ipynb
Jupyter notebooks/near_substations.ipynb
Jupyter notebooks/polygon_to_point_in_road_network.ipynb
Jupyter notebooks/raster_resampling.ipynb
Jupyter notebooks/road_network.ipynb
Jupyter notebooks/solar_potential.ipynb
Jupyter notebooks/travel_time.ipynb
_scripts/__init__.py
_scripts/biomass_solar.py
_scripts/build_solar_polygons.py
_scripts/gdal_polygonize.py
_scripts/grass_test.py
_scripts/handle_function.py
_scripts/listener_example.py
_scripts/logger_test.py
_scripts/mesh_test.py
_scripts/networks.py
_scripts/overlay_test.py
_scripts/plot_pandas_series.py
_scripts/plot_pv_power.py
_scripts/polygonize.py
_scripts/sieve.py
_scripts/solar_map.py
_scripts/solar_polygon_list.py
_scripts/surface_computation.py
_scripts/temp-plot.html
_scripts/test_contour.py
_scripts/test_metis.py
_scripts/test_multiprocessing.py
_scripts/test_net_cdf.py
_scripts/test_numba_pvlib.py
_scripts/test_print.py
_scripts/test_script_shell.py
_scripts/thread_progress.py
bash/download_osm.sh
config files/Biomass/biomass.config
config files/Biomass/biomass_generation.config
config files/Biomass/biomass_resource.config
config files/Biomass/biomass_transportation.config
config files/Biomass/distance.csv
config files/Biomass/distance_to_generation.csv
config files/Biomass/distance_to_resource.csv
config files/Biomass/mask.csv
config files/Energy system models/pv_model.config
config files/Main configuration/main.config
config files/Mixed generation/mixed_generation.config
config files/Network/Grid/grid.config
config files/Network/Road network/road_network.config
config files/Network/Road network/road_network_directions.csv
config files/Network/Road network/road_network_infrastructure.csv
greece.egg-info/PKG-INFO
greece.egg-info/SOURCES.txt
greece.egg-info/dependency_links.txt
greece.egg-info/not-zip-safe
greece.egg-info/requires.txt
greece.egg-info/top_level.txt
