Metadata-Version: 2.1
Name: greece
Version: 0.12.3
Summary: GREECE model
Home-page: http://github.com/benjamin2b/greece
Author: Benjamin Pillot
Author-email: benjaminpillot@riseup.net
License: GNU GPL v3.0
Platform: UNKNOWN
